datarun/__init__.py
datarun/check.py
datarun/chimeclassifier.py
datarun/dfcleanse.py
datarun/linear_regression.py
datarun/utils.py
datarun-0.2.6.dist-info/licenses/LICENSE
datarun-0.2.6.dist-info/METADATA
datarun-0.2.6.dist-info/WHEEL
datarun-0.2.6.dist-info/top_level.txt
datarun-0.2.6.dist-info/RECORD
