Metadata-Version: 2.4
Name: datarun
Version: 0.2.6
Summary: A simple data cleansing tool using pandas and Machine learning models
Home-page: https://github.com/arunsundark01/datarun
Author: Arun Sundar K
Author-email: karthicksundar2001@gmail.com
License: MIT
Classifier: Programming Language :: Python :: 3
Classifier: License :: OSI Approved :: MIT License
Classifier: Operating System :: OS Independent
Requires-Python: >=3.8
License-File: LICENSE
Requires-Dist: pandas
Dynamic: author
Dynamic: author-email
Dynamic: classifier
Dynamic: description
Dynamic: description-content-type
Dynamic: home-page
Dynamic: license-file
Dynamic: requires-dist
Dynamic: requires-python
Dynamic: summary
